np_calc/__init__.py
np_calc/np_operations.py
np_calc-0.2.0.dist-info/METADATA
np_calc-0.2.0.dist-info/WHEEL
np_calc-0.2.0.dist-info/RECORD
