Metadata-Version: 2.3
Name: np-calc
Version: 0.2.0
Summary: np calc library
Author: esteban-rj
Author-email: estebanelias27@gmail.com
Requires-Python: >=3.12
Classifier: Programming Language :: Python :: 3
Classifier: Programming Language :: Python :: 3.12
Classifier: Programming Language :: Python :: 3.13
Requires-Dist: numpy (>=2.2.5,<3.0.0)
